{
    "average_entropy_rate": 0.20234930042353103,
    "entropy_rate": [
        0.7863118338836691,
        0.7863118338836691,
        0.7863118338836691,
        0.7512528281680962,
        0.7863118338836691,
        0.532706550882832,
        0.0,
        0.0,
        0.0,
        0.0,
        0.0,
        0.0,
        0.0,
        0.0,
        0.0,
        0.0,
        0.0,
        0.0,
        0.0,
        0.0,
        0.0,
        0.0,
        0.0,
        0.0,
        0.0,
        0.0,
        0.0,
        0.0,
        0.0,
        0.0,
        0.0,
        0.0,
        0.0,
        0.7863118338836691,
        0.7863118338836691,
        0.7863118338836691,
        0.884799094775908,
        0.6233800063522507,
        0.0,
        0.0,
        0.0
    ],
    "estimated_posterior_probability": 56.46952819824219,
    "input": "smaller_in/ai_out_long74.txt",
    "prevalence_assumed": 0.5,
    "process_length": 80000
}