{
    "average_entropy_rate": 0.04027057555980327,
    "entropy_rate": [
        0.0,
        0.299999997655753,
        0.0,
        0.0,
        0.0,
        0.0,
        0.0,
        0.0,
        0.0,
        0.0,
        0.0,
        0.0,
        0.0,
        0.0,
        0.0,
        0.0,
        0.5454545411922779,
        0.0,
        0.0,
        0.0,
        0.0,
        0.0,
        0.0,
        0.0,
        0.0,
        0.0,
        0.0,
        0.0,
        0.0,
        0.0,
        0.0,
        0.0,
        0.0,
        0.39999999687433707,
        0.0,
        0.0,
        0.4056390622295663,
        0.0,
        0.0,
        0.0,
        0.0
    ],
    "estimated_posterior_probability": 51.12128448486328,
    "input": "smaller_in/Guten_index98.txt",
    "prevalence_assumed": 0.5,
    "process_length": 80000
}