{
    "average_entropy_rate": 0.13192414231856064,
    "entropy_rate": [
        0.7142199369175264,
        0.3793034527120736,
        0.0,
        0.0,
        0.0,
        0.0,
        0.0,
        0.0,
        0.0,
        0.0,
        0.0,
        0.0,
        0.0,
        0.0,
        0.0,
        0.0,
        0.0,
        0.7507757510667731,
        0.0,
        0.741312094477623,
        0.0,
        0.0,
        0.0,
        0.0,
        0.0,
        0.0,
        0.0,
        0.0,
        0.0,
        0.0,
        0.0,
        0.0,
        0.742632630183506,
        0.5975390189514493,
        0.0,
        0.0,
        0.0,
        0.0,
        0.8107133950540928,
        0.6723935556979433,
        0.0
    ],
    "estimated_posterior_probability": 53.96140670776367,
    "input": "./smaller_in/Guten_index4083.txt",
    "prevalence_assumed": 0.5,
    "process_length": 80000
}