{
    "average_entropy_rate": 0.23423403249357178,
    "entropy_rate": [
        0.9302849666860312,
        0.8406420682948198,
        0.8660390043033568,
        0.6478688957233579,
        0.6478688957233579,
        0.6478688957233579,
        0.6170110182976568,
        0.0,
        0.0,
        0.0,
        0.0,
        0.0,
        0.0,
        0.0,
        0.0,
        0.0,
        0.0,
        0.0,
        0.0,
        0.0,
        0.0,
        0.0,
        0.0,
        0.0,
        0.0,
        0.0,
        0.0,
        0.0,
        0.0,
        0.0,
        0.0,
        0.0,
        0.6478688957233579,
        0.9302849666860312,
        0.8406420682948198,
        0.0,
        0.6914778653335816,
        0.6478688957233579,
        0.6478688957233579,
        0.0,
        0.0
    ],
    "estimated_posterior_probability": 57.71449279785156,
    "input": "./smaller_in/Guten_index2589.txt",
    "prevalence_assumed": 0.5,
    "process_length": 80000
}