{
    "average_entropy_rate": 0.07301287745460716,
    "entropy_rate": [
        0.0,
        0.0,
        0.0,
        0.0,
        0.0,
        0.0,
        0.0,
        0.0,
        0.0,
        0.0,
        0.7452690050455688,
        0.6037269259757023,
        0.0,
        0.0,
        0.0,
        0.0,
        0.0,
        0.0,
        0.0,
        0.3088812999069436,
        0.0,
        0.0,
        0.0,
        0.0,
        0.0,
        0.0,
        0.0,
        0.0,
        0.0,
        0.0,
        0.0,
        0.0,
        0.0,
        0.0,
        0.0,
        0.0,
        0.7518273413390023,
        0.0,
        0.583823403371676,
        0.0,
        0.0
    ],
    "estimated_posterior_probability": 52.08564376831055,
    "input": "./smaller_in/Guten_index2190.txt",
    "prevalence_assumed": 0.5,
    "process_length": 80000
}